{
    "audioports": "-",
    "availability": "Discontinued",
    "bluetooth": "-",
    "bootloader": "U-Boot",
    "brand": "ALFA Network",
    "buttoncount": "2",
    "commentinstallation": null,
    "commentrecovery": null,
    "comments": null,
    "commentsavports": null,
    "commentsnetworkports": null,
    "commentsusbsataports": null,
    "cpu": "MediaTek MT7620A",
    "cpucores": "1",
    "cpumhz": "580",
    "detachableantennas": "2",
    "device_techdata": "View/Edit data",
    "devicepage": null,
    "devicetype": "WiFi Router",
    "ethernet100mports": "2",
    "ethernet10gports": "\u00bf",
    "ethernet1gports": "-",
    "ethernet2_5gports": "\u00bf",
    "ethernet5gports": "\u00bf",
    "ethernetgbitports": null,
    "fccid": null,
    "firmwareoemstockurl": null,
    "firmwareopenwrtinstallurl": null,
    "firmwareopenwrtsnapshotinstallurl": null,
    "firmwareopenwrtsnapshotupgradeurl": "https://downloads.openwrt.org/snapshots/targets/ramips/mt7620/openwrt-ramips-mt7620-alfa-network_r36m-e4g-squashfs-sysupgrade.bin",
    "firmwareopenwrtupgradeurl": "https://downloads.openwrt.org/releases/23.05.0/targets/ramips/mt7620/openwrt-23.05.0-ramips-mt7620-alfa-network_r36m-e4g-squashfs-sysupgrade.bin",
    "flashmb": "16",
    "forumsearch": "R36M-E4G",
    "gitsearch": "R36M-E4G",
    "gpios": "\u00bf",
    "id": "alfa_network_r36m-e4g",
    "installationmethods": "Sysupgrade,U-Boot web recovery,see git-commit",
    "jtag": "\u00bf",
    "ledcount": "8",
    "lede_forum_topic_url": null,
    "model": "R36M-E4G",
    "modem": "-",
    "oemdevicehomepageurl": null,
    "owrt_forum_topic_url": null,
    "packagearchitecture": "mipsel_24kc",
    "page": "toh:hwdata:alfa_network:alfa_network_r36m-e4g",
    "phoneports": "-",
    "picture": "media:example:genericrouter1.png",
    "pid": "15667937",
    "powersupply": "12 VDC",
    "rammb": "64",
    "recoverymethods": "U-Boot web recovery",
    "sataports": "-",
    "serial": "Yes",
    "serialconnectionparameters": "\u00bf",
    "sfp_plus_ports": "\u00bf",
    "sfp_ports": "\u00bf",
    "subtarget": "mt7620",
    "supportedcurrentrel": "23.05.0",
    "supportedsincecommit": "https://git.openwrt.org/?p=openwrt/openwrt.git;a=commit;h=dfecf94c2059998411f95067de3866aa7cdf5ec9",
    "supportedsincerel": "19.07.0",
    "switch": "\u00bf",
    "target": "ramips",
    "unsupported_functions": null,
    "usbports": "-",
    "version": null,
    "videoports": "-",
    "vlan": "\u00bf",
    "whereavailable": null,
    "wikideviurl": null,
    "wlan24ghz": "b/g/n",
    "wlan50ghz": "-",
    "wlancomments": null,
    "wlandriver": "mt76",
    "wlanhardware": "MediaTek MT7620A"
}