{
    "audioports": "-",
    "availability": "Discontinued",
    "bluetooth": "-",
    "bootloader": "CFE",
    "brand": "Arcadyan / Astoria",
    "buttoncount": "2",
    "commentinstallation": null,
    "commentrecovery": null,
    "comments": null,
    "commentsavports": null,
    "commentsnetworkports": null,
    "commentsusbsataports": null,
    "cpu": "Broadcom BCM6328",
    "cpucores": "1",
    "cpumhz": "320",
    "detachableantennas": "-",
    "device_techdata": "View/Edit data",
    "devicepage": "toh:arcadyan:ar7516",
    "devicetype": "WiFi Router",
    "ethernet100mports": "4",
    "ethernet10gports": "-",
    "ethernet1gports": "-",
    "ethernet2_5gports": "-",
    "ethernet5gports": "-",
    "ethernetgbitports": null,
    "fccid": null,
    "firmwareoemstockurl": null,
    "firmwareopenwrtinstallurl": "https://downloads.openwrt.org/releases/23.05.0/targets/bmips/bcm6328/openwrt-23.05.0-bmips-bcm6328-arcadyan_ar7516-squashfs-cfe.bin",
    "firmwareopenwrtsnapshotinstallurl": "https://downloads.openwrt.org/snapshots/targets/bmips/bcm6328/openwrt-bmips-bcm6328-arcadyan_ar7516-squashfs-cfe.bin",
    "firmwareopenwrtsnapshotupgradeurl": "https://downloads.openwrt.org/snapshots/targets/bmips/bcm6328/openwrt-bmips-bcm6328-arcadyan_ar7516-squashfs-sysupgrade.bin",
    "firmwareopenwrtupgradeurl": "https://downloads.openwrt.org/releases/23.05.0/targets/bmips/bcm6328/openwrt-23.05.0-bmips-bcm6328-arcadyan_ar7516-squashfs-sysupgrade.bin",
    "flashmb": "8",
    "forumsearch": "AR7516",
    "gitsearch": "AR7516",
    "gpios": "-",
    "id": "arcadyanastoria_ar7516",
    "installationmethods": "CFE web recovery,see devicepage",
    "jtag": "\u00bf",
    "ledcount": "7",
    "lede_forum_topic_url": null,
    "model": "AR7516",
    "modem": "ADSL2+",
    "oemdevicehomepageurl": null,
    "owrt_forum_topic_url": "https://forum.openwrt.org/viewtopic.php?id=43883",
    "packagearchitecture": "mips_mips32",
    "page": "toh:hwdata:arcadyanastoria:arcadyanastoria_ar7516",
    "phoneports": "-",
    "picture": "media:Arcadyan/ar7516/ar7516_orange_bright_box_1.jpg",
    "pid": "15676562",
    "powersupply": "12 VDC, 1.0 A",
    "rammb": "64",
    "recoverymethods": "CFE web recovery",
    "sataports": "-",
    "serial": "Yes",
    "serialconnectionparameters": "115200 / 8N1",
    "sfp_plus_ports": "-",
    "sfp_ports": "-",
    "subtarget": "bcm6328",
    "supportedcurrentrel": "23.05.0",
    "supportedsincecommit": "https://git.openwrt.org/?p=openwrt/openwrt.git;a=commit;h=df8e4b6c2e6440bc9a31467de1739c69c328e391",
    "supportedsincerel": "17.01.0",
    "switch": "integrated Broadcom BCM63xx",
    "target": "bmips",
    "unsupported_functions": "DSL modem,WiFi 2.4GHz partly",
    "usbports": "1x 2.0",
    "version": null,
    "videoports": "-",
    "vlan": "Yes",
    "whereavailable": null,
    "wikideviurl": "https://wikidevi.wi-cat.ru/Arcadyan_AR7516",
    "wlan24ghz": "b/g/n",
    "wlan50ghz": "-",
    "wlancomments": "2x2",
    "wlandriver": "b43",
    "wlanhardware": "Broadcom BCM43227"
}