{
    "audioports": "-",
    "availability": "Available 2020",
    "bluetooth": "-",
    "bootloader": "U-Boot",
    "brand": "Askey",
    "buttoncount": "2",
    "commentinstallation": "involves flashing with initramfs and changing the bootcmd variable in uboot",
    "commentrecovery": null,
    "comments": "This device is marketed by Spectrum as RAC2V1K but the OEM name is used because there are different revisions",
    "commentsavports": null,
    "commentsnetworkports": null,
    "commentsusbsataports": null,
    "cpu": "Qualcomm Atheros IPQ8065",
    "cpucores": "2",
    "cpumhz": "1700",
    "detachableantennas": "-",
    "device_techdata": "View/Edit data",
    "devicepage": "inbox:toh:askey:rt4230w_rev6",
    "devicetype": "WiFi Router",
    "ethernet100mports": "-",
    "ethernet10gports": "\u00bf",
    "ethernet1gports": "5",
    "ethernet2_5gports": "\u00bf",
    "ethernet5gports": "\u00bf",
    "ethernetgbitports": null,
    "fccid": "https://fccid.io/H8NRAC2V1K",
    "firmwareoemstockurl": "http://\u00bf",
    "firmwareopenwrtinstallurl": "https://downloads.openwrt.org/releases/23.05.0/targets/ipq806x/generic/openwrt-23.05.0-ipq806x-generic-askey_rt4230w-rev6-initramfs-uImage",
    "firmwareopenwrtsnapshotinstallurl": "https://downloads.openwrt.org/snapshots/targets/ipq806x/generic/openwrt-ipq806x-generic-askey_rt4230w-rev6-initramfs-uImage",
    "firmwareopenwrtsnapshotupgradeurl": "https://downloads.openwrt.org/snapshots/targets/ipq806x/generic/openwrt-ipq806x-generic-askey_rt4230w-rev6-squashfs-sysupgrade.bin",
    "firmwareopenwrtupgradeurl": "https://downloads.openwrt.org/releases/23.05.0/targets/ipq806x/generic/openwrt-23.05.0-ipq806x-generic-askey_rt4230w-rev6-squashfs-sysupgrade.bin",
    "flashmb": "512NAND",
    "forumsearch": "RT4230W,RAC2V1K",
    "gitsearch": "RT4230W,RAC2V1K",
    "gpios": "-",
    "id": "askey_rt4230w_rev6",
    "installationmethods": "see devicepage,see git-commit",
    "jtag": "\u00bf",
    "ledcount": "2",
    "lede_forum_topic_url": null,
    "model": "RT4230W",
    "modem": "-",
    "oemdevicehomepageurl": "https://www.askey.com.tw/wireless_RT4230W.html",
    "owrt_forum_topic_url": "https://forum.openwrt.org/t/askey-rac2v1k-support/15830",
    "packagearchitecture": "arm_cortex-a15_neon-vfpv4",
    "page": "toh:hwdata:askey:askey_rt4230w_rev6",
    "phoneports": "-",
    "picture": "media:askey:rac2v1k.png",
    "pid": "15681215",
    "powersupply": "12 VDC, 2.5 A",
    "rammb": "1024",
    "recoverymethods": "U-Boot TFTP + serial recovery",
    "sataports": "-",
    "serial": "Yes",
    "serialconnectionparameters": "115200 / 8N1",
    "sfp_plus_ports": "\u00bf",
    "sfp_ports": "\u00bf",
    "subtarget": "generic",
    "supportedcurrentrel": "23.05.0",
    "supportedsincecommit": "https://git.openwrt.org/?p=openwrt/openwrt.git;a=commit;h=da8428d277cd3373b05330cb3b4f93aef717c5ab",
    "supportedsincerel": "22.03.0",
    "switch": "Qualcomm Atheros QCA8337",
    "target": "ipq806x",
    "unsupported_functions": null,
    "usbports": "1x 3.0",
    "version": "REV6",
    "videoports": "-",
    "vlan": "Yes",
    "whereavailable": "\u00bf",
    "wikideviurl": "https://wikidevi.wi-cat.ru/Askey_RAC2V1K",
    "wlan24ghz": "b/g/n",
    "wlan50ghz": "a/n/ac",
    "wlancomments": "Wifi card is actually 2 identical chips with their own miniPCIe connections",
    "wlandriver": "ath10k-ct",
    "wlanhardware": "2x Qualcomm Atheros QCA9984 4x4"
}