{
    "audioports": "-",
    "availability": "Discontinued 2016",
    "bluetooth": "-",
    "bootloader": "CFE",
    "brand": "ASUS",
    "buttoncount": "2",
    "commentinstallation": null,
    "commentrecovery": null,
    "comments": "RT-AC56U and RT-AC56R are the same device",
    "commentsavports": null,
    "commentsnetworkports": null,
    "commentsusbsataports": null,
    "cpu": "Broadcom BCM4708A0",
    "cpucores": "2",
    "cpumhz": "800",
    "detachableantennas": "-",
    "device_techdata": "View/Edit data",
    "devicepage": "toh:asus:rt-ac56u",
    "devicetype": "WiFi Router",
    "ethernet100mports": "-",
    "ethernet10gports": "\u00bf",
    "ethernet1gports": "5",
    "ethernet2_5gports": "\u00bf",
    "ethernet5gports": "\u00bf",
    "ethernetgbitports": null,
    "fccid": "http://\u00bf",
    "firmwareoemstockurl": null,
    "firmwareopenwrtinstallurl": "https://downloads.openwrt.org/releases/23.05.0/targets/bcm53xx/generic/openwrt-23.05.0-bcm53xx-generic-asus_rt-ac56u-squashfs.trx",
    "firmwareopenwrtsnapshotinstallurl": "https://downloads.openwrt.org/snapshots/targets/bcm53xx/generic/openwrt-bcm53xx-generic-asus_rt-ac56u-squashfs.trx",
    "firmwareopenwrtsnapshotupgradeurl": "https://downloads.openwrt.org/snapshots/targets/bcm53xx/generic/openwrt-bcm53xx-generic-asus_rt-ac56u-squashfs.trx",
    "firmwareopenwrtupgradeurl": "https://downloads.openwrt.org/releases/23.05.0/targets/bcm53xx/generic/openwrt-23.05.0-bcm53xx-generic-asus_rt-ac56u-squashfs.trx",
    "flashmb": "128NAND",
    "forumsearch": "RT-AC56R",
    "gitsearch": "RT-AC56U",
    "gpios": "-",
    "id": "asus_rt-ac56r",
    "installationmethods": "GUI OEM,CFE TFTP recovery,see devicepage",
    "jtag": "\u00bf",
    "ledcount": "7",
    "lede_forum_topic_url": null,
    "model": "RT-AC56R",
    "modem": "-",
    "oemdevicehomepageurl": "https://www.asus.com/Networking/RTAC56R/",
    "owrt_forum_topic_url": "http://forum.openwrt.org/t/upcycling-asus-rt-ac56r/102343",
    "packagearchitecture": "arm_cortex-a9",
    "page": "toh:hwdata:asus:asus_rt-ac56r",
    "phoneports": "-",
    "picture": "media:example:genericrouter1.png",
    "pid": "15676600",
    "powersupply": "19 VDC, 1.75 A",
    "rammb": "256",
    "recoverymethods": "Asus Firmware Restoration tool",
    "sataports": "-",
    "serial": "\u00bf",
    "serialconnectionparameters": "\u00bf",
    "sfp_plus_ports": "\u00bf",
    "sfp_ports": "\u00bf",
    "subtarget": "generic",
    "supportedcurrentrel": "23.05.0",
    "supportedsincecommit": "https://git.openwrt.org/?p=openwrt/openwrt.git;a=commit;h=9d6e04a4f171cbf6acb8ad33b5a58fb39c9cab30",
    "supportedsincerel": "15.05",
    "switch": "Broadcom BCM4708A0",
    "target": "bcm53xx",
    "unsupported_functions": "WiFi 5GHz,WiFi 2.4GHz partly",
    "usbports": "1x 2.0,1x 3.0",
    "version": null,
    "videoports": "-",
    "vlan": "Yes",
    "whereavailable": null,
    "wikideviurl": "https://wikidevi.wi-cat.ru/ASUS_RT-AC56R",
    "wlan24ghz": "b/g/n",
    "wlan50ghz": "a/n/ac",
    "wlancomments": null,
    "wlandriver": "b43",
    "wlanhardware": "Broadcom BCM4352,Broadcom BCM43217"
}