{
    "audioports": "\u00bf",
    "availability": "unknown 2018",
    "bluetooth": "-",
    "bootloader": "U-Boot",
    "brand": "Bitmain",
    "buttoncount": "\u00bf",
    "commentinstallation": null,
    "commentrecovery": null,
    "comments": null,
    "commentsavports": null,
    "commentsnetworkports": null,
    "commentsusbsataports": null,
    "cpu": "Atheros AR9331",
    "cpucores": "1",
    "cpumhz": "400",
    "detachableantennas": "\u00bf",
    "device_techdata": "View/Edit data",
    "devicepage": "toh:bitmain:r1",
    "devicetype": "other",
    "ethernet100mports": "\u00bf",
    "ethernet10gports": "\u00bf",
    "ethernet1gports": "\u00bf",
    "ethernet2_5gports": "\u00bf",
    "ethernet5gports": "\u00bf",
    "ethernetgbitports": null,
    "fccid": null,
    "firmwareoemstockurl": null,
    "firmwareopenwrtinstallurl": "https://downloads.openwrt.org/releases/19.07.10/targets/ar71xx/generic/openwrt-19.07.10-ar71xx-generic-antrouter-r1-squashfs-factory.bin",
    "firmwareopenwrtsnapshotinstallurl": null,
    "firmwareopenwrtsnapshotupgradeurl": null,
    "firmwareopenwrtupgradeurl": "https://downloads.openwrt.org/releases/19.07.10/targets/ar71xx/generic/openwrt-19.07.10-ar71xx-generic-antrouter-r1-squashfs-sysupgrade.bin",
    "flashmb": "8",
    "forumsearch": "Antrouter R1",
    "gitsearch": "Antrouter R1",
    "gpios": "\u00bf",
    "id": "bitmain_antrouter_r1",
    "installationmethods": "unknown",
    "jtag": "\u00bf",
    "ledcount": "\u00bf",
    "lede_forum_topic_url": null,
    "model": "Antrouter R1",
    "modem": "\u00bf",
    "oemdevicehomepageurl": "https://www.bitmaintech.com/",
    "owrt_forum_topic_url": "https://forum.openwrt.org/viewtopic.php?pid=304824",
    "packagearchitecture": "mips_24kc",
    "page": "toh:hwdata:bitmain:bitmain_antrouter_r1",
    "phoneports": "\u00bf",
    "picture": "media:example:genericrouter1.png",
    "pid": "15704810",
    "powersupply": "\u00bf",
    "rammb": "64",
    "recoverymethods": "unknown",
    "sataports": "\u00bf",
    "serial": "\u00bf",
    "serialconnectionparameters": "\u00bf",
    "sfp_plus_ports": "\u00bf",
    "sfp_ports": "\u00bf",
    "subtarget": "generic",
    "supportedcurrentrel": "19.07.10",
    "supportedsincecommit": "https://git.openwrt.org/?p=openwrt/openwrt.git;a=commit;h=9242d27b4a91c2cf2e787d3a893de3a95890e717",
    "supportedsincerel": null,
    "switch": "\u00bf",
    "target": "ar71xx",
    "unsupported_functions": null,
    "usbports": "\u00bf",
    "version": null,
    "videoports": "\u00bf",
    "vlan": "\u00bf",
    "whereavailable": "\u00bf",
    "wikideviurl": null,
    "wlan24ghz": "b/g/n",
    "wlan50ghz": "-",
    "wlancomments": null,
    "wlandriver": "ath9k",
    "wlanhardware": "Atheros AR9331"
}