{
    "audioports": "-",
    "availability": "Discontinued 2020",
    "bluetooth": "-",
    "bootloader": "U-Boot",
    "brand": "Check Point",
    "buttoncount": "2",
    "commentinstallation": null,
    "commentrecovery": "Serial + kwboot tool",
    "comments": null,
    "commentsavports": null,
    "commentsnetworkports": null,
    "commentsusbsataports": null,
    "cpu": "Marvell 88F6281",
    "cpucores": "1",
    "cpumhz": "1200",
    "detachableantennas": "2",
    "device_techdata": "View/Edit data",
    "devicepage": "toh:check_point:l-50",
    "devicetype": "WiFi Router",
    "ethernet100mports": "-",
    "ethernet10gports": "\u00bf",
    "ethernet1gports": "10",
    "ethernet2_5gports": "\u00bf",
    "ethernet5gports": "\u00bf",
    "ethernetgbitports": null,
    "fccid": "https://fcc.io/PZ7/-67897",
    "firmwareoemstockurl": "http://\u00bf",
    "firmwareopenwrtinstallurl": "https://downloads.openwrt.org/releases/23.05.2/targets/kirkwood/generic/openwrt-23.05.2-kirkwood-generic-checkpoint_l-50-initramfs-uImage",
    "firmwareopenwrtsnapshotinstallurl": "https://downloads.openwrt.org/snapshots/targets/kirkwood/generic/u-boot-l-50/u-boot.kwb,https://downloads.openwrt.org/snapshots/targets/kirkwood/generic/openwrt-kirkwood-checkpoint_l-50-initramfs-uImage",
    "firmwareopenwrtsnapshotupgradeurl": "https://downloads.openwrt.org/snapshots/targets/kirkwood/generic/openwrt-kirkwood-checkpoint_l-50-squashfs-sysupgrade.bin",
    "firmwareopenwrtupgradeurl": "https://downloads.openwrt.org/releases/23.05.2/targets/kirkwood/generic/openwrt-23.05.2-kirkwood-generic-checkpoint_l-50-squashfs-sysupgrade.bin",
    "flashmb": "512NAND",
    "forumsearch": "L-50",
    "gitsearch": "L-50",
    "gpios": "-",
    "id": "check_point_l-50",
    "installationmethods": "see devicepage,see git-commit",
    "jtag": "No",
    "ledcount": "9",
    "lede_forum_topic_url": null,
    "model": "L-50",
    "modem": "ADSL",
    "oemdevicehomepageurl": "http://\u00bf",
    "owrt_forum_topic_url": null,
    "packagearchitecture": "arm_xscale",
    "page": "toh:hwdata:check_point:check_point_l-50",
    "phoneports": "-",
    "picture": "media:check_point:check_point_l-50.jpg",
    "pid": "15676740",
    "powersupply": "12 VDC, 2.5 A",
    "rammb": "512",
    "recoverymethods": "Serial",
    "sataports": "-",
    "serial": "Yes",
    "serialconnectionparameters": "115200 / 8N1",
    "sfp_plus_ports": "\u00bf",
    "sfp_ports": "\u00bf",
    "subtarget": "generic",
    "supportedcurrentrel": "23.05.2",
    "supportedsincecommit": "https://git.openwrt.org/?p=openwrt/openwrt.git;a=commit;h=67ce9aedd6d3f7995351f478e79e570c01ea71fc",
    "supportedsincerel": "21.02.0",
    "switch": "88E6171 x2",
    "target": "kirkwood",
    "unsupported_functions": "DSL modem",
    "usbports": "2x 2.0",
    "version": null,
    "videoports": "-",
    "vlan": "Yes",
    "whereavailable": "aftermarket",
    "wikideviurl": "https://wikidevi.wi-cat.ru/Check_Point_L-50W",
    "wlan24ghz": "b/g/n",
    "wlan50ghz": "-",
    "wlancomments": null,
    "wlandriver": "ath9k",
    "wlanhardware": "Atheros AR9287 (mini-PCIe)"
}