{
    "audioports": "-",
    "availability": "Available 2022",
    "bluetooth": "-",
    "bootloader": "U-Boot",
    "brand": "FriendlyARM",
    "buttoncount": "1",
    "commentinstallation": "SDcard and eMMC images available on FriendlyElec",
    "commentrecovery": null,
    "comments": "FriendlyElec posts frequent builds of their FriendlyWrt distro based on OpenWrt 22.03 branch",
    "commentsavports": null,
    "commentsnetworkports": "1G x1 (RTL8211F-CG), 2.5G x2 (RTL8125BG on PCIe bus)",
    "commentsusbsataports": null,
    "cpu": "Rockchip RK3588S",
    "cpucores": "8",
    "cpumhz": "2400",
    "detachableantennas": "-",
    "device_techdata": "View/Edit data",
    "devicepage": null,
    "devicetype": "Single Board Computer",
    "ethernet100mports": "-",
    "ethernet10gports": "-",
    "ethernet1gports": "1",
    "ethernet2_5gports": "2",
    "ethernet5gports": "-",
    "ethernetgbitports": null,
    "fccid": null,
    "firmwareoemstockurl": "https://drive.google.com/drive/folders/1IaLMXy-u7gs1WVFMW7fWAyP3umvDaCax",
    "firmwareopenwrtinstallurl": null,
    "firmwareopenwrtsnapshotinstallurl": null,
    "firmwareopenwrtsnapshotupgradeurl": null,
    "firmwareopenwrtupgradeurl": null,
    "flashmb": "more than 8GB eMMC,microSD,microSDHC,microSDXC",
    "forumsearch": "NanoPi R6S",
    "gitsearch": "NanoPi R6S",
    "gpios": "8",
    "id": "friendlyarm_nanopi_r6s",
    "installationmethods": "SD card",
    "jtag": null,
    "ledcount": "4",
    "lede_forum_topic_url": null,
    "model": "NanoPi R6S",
    "modem": "-",
    "oemdevicehomepageurl": "https://wiki.friendlyelec.com/wiki/index.php/NanoPi_R6S",
    "owrt_forum_topic_url": "https://forum.openwrt.org/t/nanopi-r6s-a-rockchip-rk3588s-router/141059",
    "packagearchitecture": "aarch64_generic",
    "page": "toh:hwdata:friendlyarm:friendlyarm_nanopi_r6s",
    "phoneports": "-",
    "picture": "media:friendlyarm:r6s_01-900x630.jpg",
    "pid": "24431422",
    "powersupply": "5 VDC, 3.0 A",
    "rammb": "8192",
    "recoverymethods": "SD card",
    "sataports": "-",
    "serial": "Yes",
    "serialconnectionparameters": "1500000 8N1",
    "sfp_plus_ports": "-",
    "sfp_ports": "-",
    "subtarget": "armv8",
    "supportedcurrentrel": "external image",
    "supportedsincecommit": null,
    "supportedsincerel": "external image",
    "switch": null,
    "target": "rockchip",
    "unsupported_functions": null,
    "usbports": "1x 2.0,1x 3.0,1x USB-C (power)",
    "version": null,
    "videoports": "HDMI 2.1",
    "vlan": "Yes",
    "whereavailable": "friendlyelec.com, amazon.com, aliexpress.com",
    "wikideviurl": null,
    "wlan24ghz": "-",
    "wlan50ghz": "-",
    "wlancomments": null,
    "wlandriver": null,
    "wlanhardware": null
}