{
    "audioports": "-",
    "availability": "Discontinued",
    "bluetooth": "-",
    "bootloader": "U-Boot",
    "brand": "HiWiFi/Gee",
    "buttoncount": "\u00bf",
    "commentinstallation": null,
    "commentrecovery": null,
    "comments": null,
    "commentsavports": null,
    "commentsnetworkports": null,
    "commentsusbsataports": null,
    "cpu": "MediaTek MT7620A",
    "cpucores": "1",
    "cpumhz": "580",
    "detachableantennas": "-",
    "device_techdata": "View/Edit data",
    "devicepage": "toh:hiwifi:hc5661",
    "devicetype": "WiFi Router",
    "ethernet100mports": "2",
    "ethernet10gports": "\u00bf",
    "ethernet1gports": "1",
    "ethernet2_5gports": "\u00bf",
    "ethernet5gports": "\u00bf",
    "ethernetgbitports": null,
    "fccid": null,
    "firmwareoemstockurl": null,
    "firmwareopenwrtinstallurl": null,
    "firmwareopenwrtsnapshotinstallurl": null,
    "firmwareopenwrtsnapshotupgradeurl": "https://downloads.openwrt.org/snapshots/targets/ramips/mt7620/openwrt-ramips-mt7620-hiwifi_hc5861-squashfs-sysupgrade.bin",
    "firmwareopenwrtupgradeurl": "https://downloads.openwrt.org/releases/23.05.0/targets/ramips/mt7620/openwrt-23.05.0-ramips-mt7620-hiwifi_hc5861-squashfs-sysupgrade.bin",
    "flashmb": "16",
    "forumsearch": "HC5861",
    "gitsearch": "HC5861",
    "gpios": "-",
    "id": "hiwifi_gee_hc5861",
    "installationmethods": "see devicepage",
    "jtag": "\u00bf",
    "ledcount": "\u00bf",
    "lede_forum_topic_url": null,
    "model": "HC5861",
    "modem": "-",
    "oemdevicehomepageurl": "http://www.hiwifi.com",
    "owrt_forum_topic_url": null,
    "packagearchitecture": "mipsel_24kc",
    "page": "toh:hwdata:hiwifi_gee:hiwifi_gee_hc5861",
    "phoneports": "-",
    "picture": "media:example:genericrouter1.png",
    "pid": "15677075",
    "powersupply": "\u00bf",
    "rammb": "128",
    "recoverymethods": null,
    "sataports": "\u00bf",
    "serial": "\u00bf",
    "serialconnectionparameters": "\u00bf",
    "sfp_plus_ports": "\u00bf",
    "sfp_ports": "\u00bf",
    "subtarget": "mt7620",
    "supportedcurrentrel": "23.05.0",
    "supportedsincecommit": "https://git.lede-project.org/?p=source.git;a=commit;h=dd8f5abb23c7222e427ad10703164c9aef13b148",
    "supportedsincerel": "17.01.0",
    "switch": "\u00bf",
    "target": "ramips",
    "unsupported_functions": null,
    "usbports": "\u00bf",
    "version": null,
    "videoports": "-",
    "vlan": "\u00bf",
    "whereavailable": null,
    "wikideviurl": null,
    "wlan24ghz": "\u00bf",
    "wlan50ghz": "\u00bf",
    "wlancomments": null,
    "wlandriver": "unknown",
    "wlanhardware": "\u00bf"
}