{
    "audioports": "-",
    "availability": "Discontinued",
    "bluetooth": "-",
    "bootloader": "U-Boot",
    "brand": "HooToo",
    "buttoncount": "1",
    "commentinstallation": null,
    "commentrecovery": null,
    "comments": null,
    "commentsavports": null,
    "commentsnetworkports": null,
    "commentsusbsataports": null,
    "cpu": "Ralink RT5350F",
    "cpucores": "1",
    "cpumhz": "360",
    "detachableantennas": "-",
    "device_techdata": "View/Edit data",
    "devicepage": "toh:hootoo:ht-tm01_tripmate",
    "devicetype": "Travel Router - Battery powered",
    "ethernet100mports": "1",
    "ethernet10gports": "\u00bf",
    "ethernet1gports": "-",
    "ethernet2_5gports": "\u00bf",
    "ethernet5gports": "\u00bf",
    "ethernetgbitports": null,
    "fccid": null,
    "firmwareoemstockurl": "https://www.hootoo.com/downloads-HT-TM01.html",
    "firmwareopenwrtinstallurl": "https://downloads.openwrt.org/releases/19.07.10/targets/ramips/rt305x/openwrt-19.07.10-ramips-rt305x-ht-tm02-initramfs-kernel.bin",
    "firmwareopenwrtsnapshotinstallurl": null,
    "firmwareopenwrtsnapshotupgradeurl": null,
    "firmwareopenwrtupgradeurl": "https://downloads.openwrt.org/releases/19.07.10/targets/ramips/rt305x/openwrt-19.07.10-ramips-rt305x-ht-tm02-squashfs-sysupgrade.bin",
    "flashmb": "8",
    "forumsearch": "HooToo,HT-TM01,TripMate",
    "gitsearch": "HooToo,HT-TM01,TripMate",
    "gpios": "-",
    "id": "hootoo_ht-tm01",
    "installationmethods": "see devicepage",
    "jtag": "No",
    "ledcount": "5",
    "lede_forum_topic_url": null,
    "model": "HT-TM01 (TripMate)",
    "modem": "-",
    "oemdevicehomepageurl": "https://www.hootoo.com/hootoo-tripmate-ht-tm01-wireless-router.html",
    "owrt_forum_topic_url": "https://forum.openwrt.org/viewtopic.php?id=46517,https://forum.openwrt.org/t/hootoo-ht-tm01-how-to-flash-stock-firmware/31436?u=tmomas",
    "packagearchitecture": "mipsel_24kc",
    "page": "toh:hwdata:hootoo:hootoo_ht-tm01",
    "phoneports": "-",
    "picture": "media:hootoo:hootoo-ht-tm01-tripmate_02.jpg",
    "pid": "15677086",
    "powersupply": "5 VDC, 1.5 A (\u00b5USB), 6000 mAh battery",
    "rammb": "32",
    "recoverymethods": null,
    "sataports": "-",
    "serial": "Yes",
    "serialconnectionparameters": "57600 / 8N1",
    "sfp_plus_ports": "\u00bf",
    "sfp_ports": "\u00bf",
    "subtarget": "rt305x",
    "supportedcurrentrel": "19.07.10",
    "supportedsincecommit": null,
    "supportedsincerel": "15.05",
    "switch": "-",
    "target": "ramips",
    "unsupported_functions": null,
    "usbports": "1x 2.0,1x \u00b5USB (charging)",
    "version": null,
    "videoports": "-",
    "vlan": "\u00bf",
    "whereavailable": null,
    "wikideviurl": "https://wikidevi.wi-cat.ru/HooToo_TripMate",
    "wlan24ghz": "b/g/n",
    "wlan50ghz": "-",
    "wlancomments": null,
    "wlandriver": "unknown",
    "wlanhardware": "Ralink RT5350F"
}