{
    "audioports": "-",
    "availability": "Discontinued",
    "bluetooth": "-",
    "bootloader": "CFE",
    "brand": "Huawei",
    "buttoncount": "4",
    "commentinstallation": null,
    "commentrecovery": null,
    "comments": null,
    "commentsavports": null,
    "commentsnetworkports": null,
    "commentsusbsataports": null,
    "cpu": "Broadcom BCM6358",
    "cpucores": "2",
    "cpumhz": "300",
    "detachableantennas": "-",
    "device_techdata": "View/Edit data",
    "devicepage": "toh:huawei:hg556a",
    "devicetype": "WiFi Router",
    "ethernet100mports": "4",
    "ethernet10gports": "-",
    "ethernet1gports": "-",
    "ethernet2_5gports": "-",
    "ethernet5gports": "-",
    "ethernetgbitports": null,
    "fccid": null,
    "firmwareoemstockurl": null,
    "firmwareopenwrtinstallurl": "https://downloads.openwrt.org/releases/23.05.0/targets/bcm63xx/generic/openwrt-23.05.0-bcm63xx-generic-huawei_echolife-hg556a-b-squashfs-cfe.bin",
    "firmwareopenwrtsnapshotinstallurl": "https://downloads.openwrt.org/snapshots/targets/bcm63xx/generic/openwrt-bcm63xx-generic-huawei_echolife-hg556a-b-squashfs-cfe.bin",
    "firmwareopenwrtsnapshotupgradeurl": "https://downloads.openwrt.org/snapshots/targets/bcm63xx/generic/openwrt-bcm63xx-generic-huawei_echolife-hg556a-b-squashfs-cfe.bin",
    "firmwareopenwrtupgradeurl": "https://downloads.openwrt.org/releases/23.05.0/targets/bcm63xx/generic/openwrt-23.05.0-bcm63xx-generic-huawei_echolife-hg556a-b-squashfs-cfe.bin",
    "flashmb": "16",
    "forumsearch": "HG556a",
    "gitsearch": "HG556a",
    "gpios": "-",
    "id": "huawei_hg556a_b",
    "installationmethods": "CFE TFTP + serial recovery,CFE web recovery,see devicepage",
    "jtag": "Yes",
    "ledcount": "12",
    "lede_forum_topic_url": null,
    "model": "HG556a",
    "modem": "ADSL2+",
    "oemdevicehomepageurl": null,
    "owrt_forum_topic_url": null,
    "packagearchitecture": "mips_mips32",
    "page": "toh:hwdata:huawei:huawei_hg556a_b",
    "phoneports": "2",
    "picture": "media:huawei:hg556:hg556a.png",
    "pid": "15677098",
    "powersupply": "12 VDC, 2.0 A",
    "rammb": "64",
    "recoverymethods": "CFE TFTP + serial recovery,CFE web recovery",
    "sataports": "-",
    "serial": "Yes",
    "serialconnectionparameters": "115200 / 8N1",
    "sfp_plus_ports": "-",
    "sfp_ports": "-",
    "subtarget": "generic",
    "supportedcurrentrel": "23.05.0",
    "supportedsincecommit": "https://git.lede-project.org/?p=source.git;a=commit;h=e952eaa112417637d67f1774e641c1cade49ed23",
    "supportedsincerel": "14.07",
    "switch": "Broadcom BCM5325",
    "target": "bcm63xx",
    "unsupported_functions": "DSL modem,FXS,2nd core",
    "usbports": "3x 2.0",
    "version": "B",
    "videoports": "-",
    "vlan": "Yes",
    "whereavailable": null,
    "wikideviurl": null,
    "wlan24ghz": "b/g/n",
    "wlan50ghz": "-",
    "wlancomments": null,
    "wlandriver": "ath9k",
    "wlanhardware": "Atheros AR9223"
}