{
    "audioports": "-",
    "availability": "Available 2023",
    "bluetooth": "4.1",
    "bootloader": "U-Boot",
    "brand": "Linksys",
    "buttoncount": "1",
    "commentinstallation": null,
    "commentrecovery": null,
    "comments": null,
    "commentsavports": null,
    "commentsnetworkports": null,
    "commentsusbsataports": null,
    "cpu": "Qualcomm IPQ4019",
    "cpucores": "4",
    "cpumhz": "717",
    "detachableantennas": "-",
    "device_techdata": "View/Edit data",
    "devicepage": "toh:linksys:whw03_v2",
    "devicetype": "WiFi Router",
    "ethernet100mports": "-",
    "ethernet10gports": "\u00bf",
    "ethernet1gports": "2",
    "ethernet2_5gports": "\u00bf",
    "ethernet5gports": "\u00bf",
    "ethernetgbitports": null,
    "fccid": "https://fcc.io/Q87-WHW03",
    "firmwareoemstockurl": "https://www.linksys.com/support-article?articleNum=207568",
    "firmwareopenwrtinstallurl": "http://\u00bf",
    "firmwareopenwrtsnapshotinstallurl": "https://downloads.openwrt.org/snapshots/targets/ipq40xx/generic/openwrt-ipq40xx-generic-linksys_whw03v2-squashfs-factory.bin",
    "firmwareopenwrtsnapshotupgradeurl": "https://downloads.openwrt.org/snapshots/targets/ipq40xx/generic/openwrt-ipq40xx-generic-linksys_whw03v2-squashfs-factory.bin",
    "firmwareopenwrtupgradeurl": "http://\u00bf",
    "flashmb": "512",
    "forumsearch": "WHW03",
    "gitsearch": "WHW03",
    "gpios": "-",
    "id": "linksys_whw03_v2",
    "installationmethods": "GUI OEM",
    "jtag": "No",
    "ledcount": "1",
    "lede_forum_topic_url": null,
    "model": "WHW03",
    "modem": "-",
    "oemdevicehomepageurl": "https://www.linksys.com/whw0301---tri-band-intelligent-mesh-wifi-5-router/WHW0301.html",
    "owrt_forum_topic_url": null,
    "packagearchitecture": "arm_cortex-a7_neon-vfpv4",
    "page": "toh:hwdata:linksys:linksys_whw03_v2",
    "phoneports": "-",
    "picture": "media:linksys_whw03v2.jpg",
    "pid": "25002233",
    "powersupply": "12 VDC, 2 Amp",
    "rammb": "512",
    "recoverymethods": "Linksys TFTP",
    "sataports": "-",
    "serial": "Yes",
    "serialconnectionparameters": "115200 / 8N1",
    "sfp_plus_ports": "\u00bf",
    "sfp_ports": "\u00bf",
    "subtarget": "generic",
    "supportedcurrentrel": "snapshot",
    "supportedsincecommit": "https://git.openwrt.org/?p=openwrt/openwrt.git;a=commit;h=9e4ede8344d60d4837e047e9275c21fd2a8f130b",
    "supportedsincerel": null,
    "switch": "Qualcomm Atheros QCA8072",
    "target": "ipq40xx",
    "unsupported_functions": null,
    "usbports": "-",
    "version": "V2",
    "videoports": "-",
    "vlan": "Yes",
    "whereavailable": "amazon.com",
    "wikideviurl": "https://wikidevi.wi-cat.ru/Linksys_Velop_(WHW03_V2)",
    "wlan24ghz": "b/g/n",
    "wlan50ghz": "a/n/ac",
    "wlancomments": null,
    "wlandriver": "ath10k,ath10k-ct",
    "wlanhardware": "Qualcomm IPQ4019"
}