{
    "audioports": "-",
    "availability": "Available 2019",
    "bluetooth": "-",
    "bootloader": "RouterBOOT",
    "brand": "MikroTik",
    "buttoncount": "\u00bf",
    "commentinstallation": null,
    "commentrecovery": null,
    "comments": "NAND snapshot image build disabled with commit 9d96b6fb720d9cecc",
    "commentsavports": null,
    "commentsnetworkports": null,
    "commentsusbsataports": null,
    "cpu": "Qualcomm Atheros QCA9557",
    "cpucores": "1",
    "cpumhz": "720",
    "detachableantennas": "2",
    "device_techdata": "View/Edit data",
    "devicepage": null,
    "devicetype": "WiFi Router",
    "ethernet100mports": "-",
    "ethernet10gports": "\u00bf",
    "ethernet1gports": "1",
    "ethernet2_5gports": "\u00bf",
    "ethernet5gports": "\u00bf",
    "ethernetgbitports": null,
    "fccid": null,
    "firmwareoemstockurl": null,
    "firmwareopenwrtinstallurl": "https://downloads.openwrt.org/releases/19.07.10/targets/ar71xx/mikrotik/openwrt-19.07.10-ar71xx-mikrotik-vmlinux-initramfs.elf",
    "firmwareopenwrtsnapshotinstallurl": "https://downloads.openwrt.org/snapshots/targets/ath79/nand/openwrt-ath79-nand-mikrotik_routerboard-922uags-5hpacd-initramfs-kernel.bin",
    "firmwareopenwrtsnapshotupgradeurl": "https://downloads.openwrt.org/snapshots/targets/ath79/nand/openwrt-ath79-nand-mikrotik_routerboard-922uags-5hpacd-squashfs-sysupgrade.bin",
    "firmwareopenwrtupgradeurl": "https://downloads.openwrt.org/releases/19.07.10/targets/ar71xx/mikrotik/openwrt-19.07.10-ar71xx-mikrotik-nand-large-ac-squashfs-sysupgrade.bin",
    "flashmb": "128NAND",
    "forumsearch": "RB922UAGS-5HPacD",
    "gitsearch": "RB922UAGS-5HPacD",
    "gpios": "-",
    "id": "mikrotik_rb922uags-5hpacd",
    "installationmethods": "Mikrotik TFTP,see git-commit",
    "jtag": "\u00bf",
    "ledcount": "\u00bf",
    "lede_forum_topic_url": null,
    "model": "RB922UAGS-5HPacD",
    "modem": "-",
    "oemdevicehomepageurl": "https://mikrotik.com/product/RB922UAGS-5HPacD",
    "owrt_forum_topic_url": null,
    "packagearchitecture": "mips_24kc",
    "page": "toh:hwdata:mikrotik:mikrotik_rb922uags-5hpacd",
    "phoneports": "-",
    "picture": "media:example:genericrouter1.png",
    "pid": "15677347",
    "powersupply": "8-30 VDC, passive PoE",
    "rammb": "128",
    "recoverymethods": "unknown",
    "sataports": "-",
    "serial": "\u00bf",
    "serialconnectionparameters": "\u00bf",
    "sfp_plus_ports": "\u00bf",
    "sfp_ports": "1",
    "subtarget": "mikrotik",
    "supportedcurrentrel": "19.07.10",
    "supportedsincecommit": "https://git.openwrt.org/?p=openwrt/openwrt.git;a=commit;h=e1444ab59cfcd330cfac6f51aa14106961585ee1",
    "supportedsincerel": "19.07.0",
    "switch": "-",
    "target": "ar71xx-ath79",
    "unsupported_functions": null,
    "usbports": "1x 2.0",
    "version": null,
    "videoports": "-",
    "vlan": "\u00bf",
    "whereavailable": "mikrotik-store.eu",
    "wikideviurl": null,
    "wlan24ghz": "-",
    "wlan50ghz": "a/n/ac",
    "wlancomments": null,
    "wlandriver": "ath10k-ct",
    "wlanhardware": "Qualcomm Atheros QCA9882"
}