{
    "audioports": "-",
    "availability": "Available 2021",
    "bluetooth": "-",
    "bootloader": "CFE",
    "brand": "NETGEAR",
    "buttoncount": "\u00bf",
    "commentinstallation": null,
    "commentrecovery": null,
    "comments": null,
    "commentsavports": null,
    "commentsnetworkports": null,
    "commentsusbsataports": null,
    "cpu": "Broadcom BCM4906",
    "cpucores": "2",
    "cpumhz": "1800",
    "detachableantennas": "-",
    "device_techdata": "View/Edit data",
    "devicepage": "toh:netgear:r8000p",
    "devicetype": "WiFi Router",
    "ethernet100mports": "-",
    "ethernet10gports": "\u00bf",
    "ethernet1gports": "5",
    "ethernet2_5gports": "\u00bf",
    "ethernet5gports": "\u00bf",
    "ethernetgbitports": null,
    "fccid": "https://fcc.io/PY3/16400363",
    "firmwareoemstockurl": "https://www.netgear.com/support/product/R8000P",
    "firmwareopenwrtinstallurl": "https://downloads.openwrt.org/releases/23.05.0/targets/bcm4908/generic/openwrt-23.05.0-bcm4908-generic-netgear_r8000p-squashfs.bin",
    "firmwareopenwrtsnapshotinstallurl": "https://downloads.openwrt.org/snapshots/targets/bcm4908/generic/openwrt-bcm4908-generic-netgear_r8000p-squashfs.bin",
    "firmwareopenwrtsnapshotupgradeurl": null,
    "firmwareopenwrtupgradeurl": null,
    "flashmb": "128NAND",
    "forumsearch": "R8000P",
    "gitsearch": "R8000P",
    "gpios": "-",
    "id": "netgear_r8000p",
    "installationmethods": "CFE web recovery,see git-commit",
    "jtag": "\u00bf",
    "ledcount": "\u00bf",
    "lede_forum_topic_url": null,
    "model": "R8000P",
    "modem": "-",
    "oemdevicehomepageurl": "https://www.netgear.com/home/wifi/routers/r8000p/",
    "owrt_forum_topic_url": null,
    "packagearchitecture": "aarch64_cortex-a53",
    "page": "toh:hwdata:netgear:netgear_r8000p",
    "phoneports": "-",
    "picture": "media:netgear:r8000p.jpg",
    "pid": "15682016",
    "powersupply": "19 VDC, 3.16 A",
    "rammb": "512",
    "recoverymethods": "unknown",
    "sataports": "-",
    "serial": "\u00bf",
    "serialconnectionparameters": "\u00bf",
    "sfp_plus_ports": "\u00bf",
    "sfp_ports": "\u00bf",
    "subtarget": "generic",
    "supportedcurrentrel": "23.05.0",
    "supportedsincecommit": "https://git.openwrt.org/?p=openwrt/openwrt.git;a=commit;h=d92a9c97bf3700e90af1d3c9157502af660365c0",
    "supportedsincerel": "21.02.0",
    "switch": "Broadcom BCM4906",
    "target": "bcm4908",
    "unsupported_functions": null,
    "usbports": "1x 2.0,1x 3.0",
    "version": null,
    "videoports": "-",
    "vlan": "Yes",
    "whereavailable": "amazon.de",
    "wikideviurl": "https://wikidevi.wi-cat.ru/Netgear_R8000P",
    "wlan24ghz": "b/g/n",
    "wlan50ghz": "a/n/ac",
    "wlancomments": null,
    "wlandriver": "unknown",
    "wlanhardware": "Broadcom BCM4365E"
}