{
    "audioports": "-",
    "availability": "Discontinued 2015",
    "bluetooth": "-",
    "bootloader": "U-Boot",
    "brand": "Shuttle",
    "buttoncount": "3",
    "commentinstallation": null,
    "commentrecovery": null,
    "comments": "GPL sources: http://data.shuttle.eu/~upload/omninas/KD20_20121127.zip; Factory image build disabled with commit b0b7f2b8f3a6bba4",
    "commentsavports": null,
    "commentsnetworkports": null,
    "commentsusbsataports": null,
    "cpu": "PLX NAS7821",
    "cpucores": "2",
    "cpumhz": "750",
    "detachableantennas": "-",
    "device_techdata": "View/Edit data",
    "devicepage": "toh:shuttle:kd20",
    "devicetype": "NAS",
    "ethernet100mports": "-",
    "ethernet10gports": "\u00bf",
    "ethernet1gports": "1",
    "ethernet2_5gports": "\u00bf",
    "ethernet5gports": "\u00bf",
    "ethernetgbitports": null,
    "fccid": null,
    "firmwareoemstockurl": "https://web.archive.org/web/20180730191409/http://global.shuttle.com/news/productsDownload?productId=1629",
    "firmwareopenwrtinstallurl": "https://makrotopia.org/openwrt-oxnas-kd20-factory.tar.gz",
    "firmwareopenwrtsnapshotinstallurl": "https://makrotopia.org/lede-oxnas-kd20-factory.tar.gz",
    "firmwareopenwrtsnapshotupgradeurl": "https://downloads.openwrt.org/snapshots/targets/oxnas/ox820/openwrt-oxnas-ox820-shuttle_kd20-squashfs-sysupgrade.tar",
    "firmwareopenwrtupgradeurl": "https://downloads.openwrt.org/releases/19.07.7/targets/oxnas/ox820/openwrt-19.07.7-oxnas-ox820-shuttle_kd20-squashfs-sysupgrade.tar",
    "flashmb": "128NAND",
    "forumsearch": "OMNINAS KD20",
    "gitsearch": "KD20",
    "gpios": "-",
    "id": "shuttle_omninas_kd20",
    "installationmethods": "GUI OEM,see devicepage",
    "jtag": "No",
    "ledcount": "4",
    "lede_forum_topic_url": null,
    "model": "OMNINAS KD20",
    "modem": "-",
    "oemdevicehomepageurl": "https://web.archive.org/web/20170902084135/http://global.shuttle.com/news/productsSpec?productId=1629",
    "owrt_forum_topic_url": "https://forum.openwrt.org/t/install-openwrt-on-shuttle-omninas-kd20/70465?u=tmomas",
    "packagearchitecture": "arm_mpcore",
    "page": "toh:hwdata:shuttle:shuttle_omninas_kd20",
    "phoneports": "-",
    "picture": "toh:shuttle:backend_75_201207241250_1087.png",
    "pid": "15683087",
    "powersupply": "19 VDC, 3.42 A",
    "rammb": "256",
    "recoverymethods": "U-Boot TFTP + serial recovery",
    "sataports": "2",
    "serial": "Yes",
    "serialconnectionparameters": "115200 / 8N1",
    "sfp_plus_ports": "\u00bf",
    "sfp_ports": "\u00bf",
    "subtarget": "ox820",
    "supportedcurrentrel": "19.07.7",
    "supportedsincecommit": "https://git.lede-project.org/?p=source.git;a=commit;h=72b58f2eb12ad4aa0c59481d0911dc5e39180eb5",
    "supportedsincerel": "17.01.0",
    "switch": "-",
    "target": "oxnas",
    "unsupported_functions": "SDcard,USB 3.0",
    "usbports": "2x 2.0,1x 3.0",
    "version": null,
    "videoports": "-",
    "vlan": "Yes",
    "whereavailable": null,
    "wikideviurl": null,
    "wlan24ghz": "-",
    "wlan50ghz": "-",
    "wlancomments": null,
    "wlandriver": "none",
    "wlanhardware": "-"
}