{
    "audioports": "-",
    "availability": "Available 2021",
    "bluetooth": "-",
    "bootloader": "U-Boot",
    "brand": "TOTOLINK",
    "buttoncount": "1",
    "commentinstallation": null,
    "commentrecovery": null,
    "comments": null,
    "commentsavports": null,
    "commentsnetworkports": null,
    "commentsusbsataports": null,
    "cpu": "MediaTek MT7621AT",
    "cpucores": "2",
    "cpumhz": "880",
    "detachableantennas": "-",
    "device_techdata": "View/Edit data",
    "devicepage": "toh:totolink:x5000r",
    "devicetype": "WiFi Router",
    "ethernet100mports": "-",
    "ethernet10gports": "\u00bf",
    "ethernet1gports": "5",
    "ethernet2_5gports": "\u00bf",
    "ethernet5gports": "\u00bf",
    "ethernetgbitports": null,
    "fccid": "http://\u00bf",
    "firmwareoemstockurl": "https://www.totolink.net/home/menu/detail/menu_listtpl/download/id/218/ids/36.html",
    "firmwareopenwrtinstallurl": null,
    "firmwareopenwrtsnapshotinstallurl": null,
    "firmwareopenwrtsnapshotupgradeurl": "https://downloads.openwrt.org/snapshots/targets/ramips/mt7621/openwrt-ramips-mt7621-totolink_x5000r-squashfs-sysupgrade.bin",
    "firmwareopenwrtupgradeurl": "https://downloads.openwrt.org/releases/23.05.0/targets/ramips/mt7621/openwrt-23.05.0-ramips-mt7621-totolink_x5000r-squashfs-sysupgrade.bin",
    "flashmb": "16",
    "forumsearch": "X5000R",
    "gitsearch": "X5000R",
    "gpios": "-",
    "id": "totolink_x5000r",
    "installationmethods": "GUI OEM,see git-commit",
    "jtag": "\u00bf",
    "ledcount": "6",
    "lede_forum_topic_url": null,
    "model": "X5000R",
    "modem": "-",
    "oemdevicehomepageurl": "https://www.totolink.net/home/menu/newstpl/menu_newstpl/products/id/218.html",
    "owrt_forum_topic_url": null,
    "packagearchitecture": "mipsel_24kc",
    "page": "toh:hwdata:totolink:totolink_x5000r",
    "phoneports": "-",
    "picture": "media:totolink:x5000r_product.png",
    "pid": "15667939",
    "powersupply": "12 VDC, 1.0 A",
    "rammb": "256",
    "recoverymethods": "unknown",
    "sataports": "-",
    "serial": "\u00bf",
    "serialconnectionparameters": "\u00bf",
    "sfp_plus_ports": "\u00bf",
    "sfp_ports": "\u00bf",
    "subtarget": "mt7621",
    "supportedcurrentrel": "23.05.0",
    "supportedsincecommit": "https://git.openwrt.org/?p=openwrt/openwrt.git;a=commit;h=23be410b3d1267c752bf9f6e5c8f5a514dc562c4",
    "supportedsincerel": "21.02.0",
    "switch": "\u00bf",
    "target": "ramips",
    "unsupported_functions": null,
    "usbports": "-",
    "version": null,
    "videoports": "-",
    "vlan": "\u00bf",
    "whereavailable": "aliexpress.com",
    "wikideviurl": null,
    "wlan24ghz": "b/g/n/ax",
    "wlan50ghz": "a/n/ac/ax",
    "wlancomments": null,
    "wlandriver": "mt76",
    "wlanhardware": "MediaTek MT7915DA,MediaTek MT7915DN"
}