{
    "audioports": "-",
    "availability": "Discontinued",
    "bluetooth": "-",
    "bootloader": "CFE",
    "brand": "TP-Link",
    "buttoncount": "\u00bf",
    "commentinstallation": null,
    "commentrecovery": "TFTP-Recoveryname: ArcherC9v1_tp_recovery.bin",
    "comments": null,
    "commentsavports": null,
    "commentsnetworkports": null,
    "commentsusbsataports": null,
    "cpu": "Broadcom BCM4709",
    "cpucores": "2",
    "cpumhz": "1000",
    "detachableantennas": "3",
    "device_techdata": "View/Edit data",
    "devicepage": "toh:tp-link:archer-c9",
    "devicetype": "WiFi Router",
    "ethernet100mports": "-",
    "ethernet10gports": "\u00bf",
    "ethernet1gports": "5",
    "ethernet2_5gports": "\u00bf",
    "ethernet5gports": "\u00bf",
    "ethernetgbitports": null,
    "fccid": "https://fcc.io/TE7/C9",
    "firmwareoemstockurl": null,
    "firmwareopenwrtinstallurl": "https://downloads.openwrt.org/releases/19.07.10/targets/bcm53xx/generic/openwrt-19.07.10-bcm53xx-tplink-archer-c9-v1-squashfs.bin",
    "firmwareopenwrtsnapshotinstallurl": "https://downloads.openwrt.org/snapshots/targets/bcm53xx/generic/openwrt-bcm53xx-generic-tplink-archer-c9-v1-squashfs.bin",
    "firmwareopenwrtsnapshotupgradeurl": null,
    "firmwareopenwrtupgradeurl": null,
    "flashmb": "16",
    "forumsearch": "Archer C9",
    "gitsearch": "Archer C9",
    "gpios": "-",
    "id": "tp-link_archer_c9_v1",
    "installationmethods": "CFE TFTP recovery",
    "jtag": "Yes",
    "ledcount": "\u00bf",
    "lede_forum_topic_url": null,
    "model": "Archer C9",
    "modem": "-",
    "oemdevicehomepageurl": null,
    "owrt_forum_topic_url": "https://forum.openwrt.org/viewtopic.php?pid=348343",
    "packagearchitecture": "arm_cortex-a9",
    "page": "toh:hwdata:tp-link:tp-link_archer_c9_v1",
    "phoneports": "-",
    "picture": "media:example:genericrouter1.png",
    "pid": "15677772",
    "powersupply": "12 VDC, 3.3 A",
    "rammb": "128",
    "recoverymethods": "CFE TFTP recovery,see devicepage",
    "sataports": "-",
    "serial": "Yes",
    "serialconnectionparameters": "115200 / 8N1",
    "sfp_plus_ports": "\u00bf",
    "sfp_ports": "\u00bf",
    "subtarget": "generic",
    "supportedcurrentrel": "19.07.10",
    "supportedsincecommit": "https://git.lede-project.org/?p=source.git;a=commit;h=5e339a48aa95b4c7702829c09a99ccf3b99aad3e",
    "supportedsincerel": "17.01.0",
    "switch": "Broadcom BCM4709",
    "target": "bcm53xx",
    "unsupported_functions": "WiFi 2.4GHz partly,WiFi 5GHz",
    "usbports": "1x 2.0,1x 3.0",
    "version": "v1",
    "videoports": "-",
    "vlan": "Yes",
    "whereavailable": null,
    "wikideviurl": "https://wikidevi.wi-cat.ru/TP-LINK_Archer_C9_v1.x",
    "wlan24ghz": "b/g/n",
    "wlan50ghz": "a/n/ac",
    "wlancomments": "3x3 MIMO",
    "wlandriver": "b43",
    "wlanhardware": "Broadcom BCM4360"
}