{
    "audioports": "-",
    "availability": "Discontinued 2017",
    "bluetooth": "-",
    "bootloader": "U-Boot",
    "brand": "TP-Link",
    "buttoncount": "2",
    "commentinstallation": "Rename installation image to 'ArcherC7v4_tp_recovery.bin', see git-commit",
    "commentrecovery": "rename OpenWRT factory image to 'ArcherC7v4_tp_recovery.bin', tftp from static IP 192.168.0.66 (mask 255.255.255.0, gateway 192.168.0.1); press&hold RESET on router boot to initiate recovery",
    "comments": null,
    "commentsavports": null,
    "commentsnetworkports": null,
    "commentsusbsataports": null,
    "cpu": "Qualcomm Atheros QCA9563",
    "cpucores": "1",
    "cpumhz": "775",
    "detachableantennas": "3",
    "device_techdata": "View/Edit data",
    "devicepage": "toh:tp-link:archer_c7",
    "devicetype": "WiFi Router",
    "ethernet100mports": "-",
    "ethernet10gports": "\u00bf",
    "ethernet1gports": "5",
    "ethernet2_5gports": "\u00bf",
    "ethernet5gports": "\u00bf",
    "ethernetgbitports": null,
    "fccid": "https://fcc.io/TE7/C7V4",
    "firmwareoemstockurl": "https://www.tp-link.com/en/download/Archer-C7_V4.html",
    "firmwareopenwrtinstallurl": "https://downloads.openwrt.org/releases/23.05./targets/ath79/generic/openwrt-23.05.2-ath79-generic-tplink_archer-c7-v4-squashfs-factory.bin",
    "firmwareopenwrtsnapshotinstallurl": "https://downloads.openwrt.org/snapshots/targets/ath79/generic/openwrt-ath79-generic-tplink_archer-c7-v4-squashfs-factory.bin",
    "firmwareopenwrtsnapshotupgradeurl": "https://downloads.openwrt.org/snapshots/targets/ath79/generic/openwrt-ath79-generic-tplink_archer-c7-v4-squashfs-sysupgrade.bin",
    "firmwareopenwrtupgradeurl": "https://downloads.openwrt.org/releases/23.05.2/targets/ath79/generic/openwrt-23.05.2-ath79-generic-tplink_archer-c7-v4-squashfs-sysupgrade.bin",
    "flashmb": "16",
    "forumsearch": "Archer C7 v4,Archer C7 AC1750",
    "gitsearch": "Archer C7 v4,Archer C7 AC1750",
    "gpios": "-",
    "id": "tp-link_archer_c7_v4",
    "installationmethods": "GUI OEM,U-Boot TFTP recovery,see git-commit",
    "jtag": "\u00bf",
    "ledcount": "7",
    "lede_forum_topic_url": null,
    "model": "Archer C7",
    "modem": "-",
    "oemdevicehomepageurl": "https://www.tp-link.com/en/products/details/Archer-C7.html",
    "owrt_forum_topic_url": "https://forum.openwrt.org/t/help-required-to-revert-to-stock-tp-link-archer-c7-v4-eu/17641/1",
    "packagearchitecture": "mips_24kc",
    "page": "toh:hwdata:tp-link:tp-link_archer_c7_v4",
    "phoneports": "-",
    "picture": "media:tplink:archer_c7_v4_front_official.jpg",
    "pid": "15677764",
    "powersupply": "12 VDC, 2.0 A",
    "rammb": "128",
    "recoverymethods": "U-Boot TFTP + serial recovery,see git-commit",
    "sataports": "-",
    "serial": "Yes",
    "serialconnectionparameters": "\u00bf",
    "sfp_plus_ports": "\u00bf",
    "sfp_ports": "\u00bf",
    "subtarget": "generic",
    "supportedcurrentrel": "23.05.2",
    "supportedsincecommit": "https://git.lede-project.org/?p=source.git;a=commit;h=9887afb1afcf387f6892315413e610a6816df463",
    "supportedsincerel": "18.06.0",
    "switch": "Qualcomm Atheros QCA8337N",
    "target": "ar71xx-ath79",
    "unsupported_functions": null,
    "usbports": "2x 2.0",
    "version": "v4",
    "videoports": "-",
    "vlan": "Yes",
    "whereavailable": null,
    "wikideviurl": "https://wikidevi.wi-cat.ru/TP-LINK_Archer_C7_v4.x",
    "wlan24ghz": "b/g/n",
    "wlan50ghz": "a/n/ac",
    "wlancomments": null,
    "wlandriver": "ath10k",
    "wlanhardware": "Qualcomm Atheros QCA9563,Qualcomm Atheros QCA9880"
}