{
    "audioports": "-",
    "availability": "Available 2019",
    "bluetooth": "-",
    "bootloader": "U-Boot",
    "brand": "TP-Link",
    "buttoncount": "2",
    "commentinstallation": "for instructions to create image from squashfs-sysupgrade.bin",
    "commentrecovery": "for instructions to create tp_recovery.bin image from squashfs-sysupgrade.bin",
    "comments": "Do NOT install squashfs-sysupgrade image via TPlink web UI or TFTP. It will brick router!",
    "commentsavports": null,
    "commentsnetworkports": null,
    "commentsusbsataports": null,
    "cpu": "MediaTek MT7628A",
    "cpucores": "1",
    "cpumhz": "580",
    "detachableantennas": "-",
    "device_techdata": "View/Edit data",
    "devicepage": "toh:tp-link:archer-c50",
    "devicetype": "WiFi Router",
    "ethernet100mports": "5",
    "ethernet10gports": "\u00bf",
    "ethernet1gports": "-",
    "ethernet2_5gports": "\u00bf",
    "ethernet5gports": "\u00bf",
    "ethernetgbitports": null,
    "fccid": "https://fcc.io/TE7/C50V3",
    "firmwareoemstockurl": "https://www.tp-link.com/en/support/download/archer-c50/",
    "firmwareopenwrtinstallurl": null,
    "firmwareopenwrtsnapshotinstallurl": null,
    "firmwareopenwrtsnapshotupgradeurl": "https://downloads.openwrt.org/snapshots/targets/ramips/mt76x8/openwrt-ramips-mt76x8-tplink_archer-c50-v4-squashfs-sysupgrade.bin",
    "firmwareopenwrtupgradeurl": "https://downloads.openwrt.org/releases/23.05.0/targets/ramips/mt76x8/openwrt-23.05.0-ramips-mt76x8-tplink_archer-c50-v4-squashfs-sysupgrade.bin",
    "flashmb": "8",
    "forumsearch": "Archer C50",
    "gitsearch": "Archer C50",
    "gpios": "-",
    "id": "tp-link_archer_c50_v4",
    "installationmethods": "see git-commit",
    "jtag": "\u00bf",
    "ledcount": "6",
    "lede_forum_topic_url": null,
    "model": "Archer C50",
    "modem": "-",
    "oemdevicehomepageurl": "https://www.tp-link.com/en/home-networking/wifi-router/archer-c50/",
    "owrt_forum_topic_url": "https://forum.openwrt.org/t/support-for-archer-c50-v4/20174",
    "packagearchitecture": "mipsel_24kc",
    "page": "toh:hwdata:tp-link:tp-link_archer_c50_v4",
    "phoneports": "-",
    "picture": "media/tplink/archerc50/0archerc50_v3v4_front.jpg",
    "pid": "15677781",
    "powersupply": "9 VDC, 0.85 A",
    "rammb": "64",
    "recoverymethods": "see git-commit",
    "sataports": "-",
    "serial": "Yes",
    "serialconnectionparameters": "115200 / 8N1",
    "sfp_plus_ports": "\u00bf",
    "sfp_ports": "\u00bf",
    "subtarget": "mt76x8",
    "supportedcurrentrel": "23.05.0",
    "supportedsincecommit": "https://git.openwrt.org/?p=openwrt/openwrt.git;a=commit;h=01dcd574a24864c10a9c4df4304a3ce0da5c11a9",
    "supportedsincerel": "19.07.0",
    "switch": "MediaTek MT7628A",
    "target": "ramips",
    "unsupported_functions": null,
    "usbports": "-",
    "version": "v4",
    "videoports": "-",
    "vlan": "Yes",
    "whereavailable": "alternate.de, amazon.de",
    "wikideviurl": "https://wikidevi.wi-cat.ru/TP-LINK_Archer_C50_v4.x",
    "wlan24ghz": "b/g/n",
    "wlan50ghz": "a/n/ac",
    "wlancomments": null,
    "wlandriver": "mt76",
    "wlanhardware": "MediaTek MT7628A,MediaTek MT7612E"
}