{
    "audioports": "-",
    "availability": "Discontinued",
    "bluetooth": "-",
    "bootloader": "U-Boot",
    "brand": "TP-Link",
    "buttoncount": "\u00bf",
    "commentinstallation": null,
    "commentrecovery": null,
    "comments": null,
    "commentsavports": null,
    "commentsnetworkports": null,
    "commentsusbsataports": null,
    "cpu": "Qualcomm Atheros QCA9563",
    "cpucores": "1",
    "cpumhz": "\u00bf",
    "detachableantennas": "-",
    "device_techdata": "View/Edit data",
    "devicepage": null,
    "devicetype": "other",
    "ethernet100mports": "-",
    "ethernet10gports": "\u00bf",
    "ethernet1gports": "2",
    "ethernet2_5gports": "\u00bf",
    "ethernet5gports": "\u00bf",
    "ethernetgbitports": null,
    "fccid": "https://fcc.io/TE7M4R",
    "firmwareoemstockurl": "https://www.tp-link.com/us/support/download/deco-m4/v1/",
    "firmwareopenwrtinstallurl": "https://downloads.openwrt.org/releases/23.05.0/targets/ath79/generic/openwrt-23.05.0-ath79-generic-tplink_deco-m4r-v1-squashfs-factory.bin",
    "firmwareopenwrtsnapshotinstallurl": "https://downloads.openwrt.org/snapshots/targets/ath79/generic/openwrt-ath79-generic-tplink_deco-m4r-v1-squashfs-factory.bin",
    "firmwareopenwrtsnapshotupgradeurl": "https://downloads.openwrt.org/snapshots/targets/ath79/generic/openwrt-ath79-generic-tplink_deco-m4r-v1-squashfs-sysupgrade.bin",
    "firmwareopenwrtupgradeurl": "https://downloads.openwrt.org/releases/23.05.0/targets/ath79/generic/openwrt-23.05.0-ath79-generic-tplink_deco-m4r-v1-squashfs-sysupgrade.bin",
    "flashmb": "16",
    "forumsearch": "M4R",
    "gitsearch": "M4R",
    "gpios": "-",
    "id": "tp-link_m4r_v1",
    "installationmethods": "see git-commit",
    "jtag": "\u00bf",
    "ledcount": "\u00bf",
    "lede_forum_topic_url": null,
    "model": "M4R",
    "modem": "-",
    "oemdevicehomepageurl": "https://www.tp-link.com/us/deco-mesh-wifi/product-family/deco-m4/",
    "owrt_forum_topic_url": null,
    "packagearchitecture": "mips_24kc",
    "page": "toh:hwdata:tp-link:tp-link_m4r_v1",
    "phoneports": "-",
    "picture": "media:example:genericrouter1.png",
    "pid": "21021851",
    "powersupply": "12 VDC, 1.2 A",
    "rammb": "128",
    "recoverymethods": "unknown",
    "sataports": "-",
    "serial": "\u00bf",
    "serialconnectionparameters": "\u00bf",
    "sfp_plus_ports": "\u00bf",
    "sfp_ports": "\u00bf",
    "subtarget": "generic",
    "supportedcurrentrel": "23.05.0",
    "supportedsincecommit": "https://git.openwrt.org/?p=openwrt/openwrt.git;a=commit;h=063e9047cc8b247ea4b04ee3248b99f3212a42f8",
    "supportedsincerel": "22.03.0",
    "switch": "Qualcomm Atheros QCA8337N",
    "target": "ath79",
    "unsupported_functions": null,
    "usbports": "-",
    "version": "v1",
    "videoports": "-",
    "vlan": "\u00bf",
    "whereavailable": null,
    "wikideviurl": "https://wikidevi.wi-cat.ru/TP-LINK_Deco_M4R",
    "wlan24ghz": "b/g/n",
    "wlan50ghz": "a/n/ac",
    "wlancomments": null,
    "wlandriver": "ath10k-ct",
    "wlanhardware": "Qualcomm Atheros QCA9563,Qualcomm Atheros QCA9886"
}