{
    "audioports": "-",
    "availability": "unknown 2018",
    "bluetooth": "-",
    "bootloader": "U-Boot",
    "brand": "Wallys",
    "buttoncount": "1",
    "commentinstallation": null,
    "commentrecovery": null,
    "comments": null,
    "commentsavports": null,
    "commentsnetworkports": null,
    "commentsusbsataports": null,
    "cpu": "Atheros AR9342",
    "cpucores": "1",
    "cpumhz": "560",
    "detachableantennas": "-",
    "device_techdata": "View/Edit data",
    "devicepage": null,
    "devicetype": "WiFi AP",
    "ethernet100mports": "-",
    "ethernet10gports": "\u00bf",
    "ethernet1gports": "1",
    "ethernet2_5gports": "\u00bf",
    "ethernet5gports": "\u00bf",
    "ethernetgbitports": null,
    "fccid": null,
    "firmwareoemstockurl": null,
    "firmwareopenwrtinstallurl": "https://downloads.openwrt.org/releases/19.07.10/targets/ar71xx/generic/openwrt-19.07.10-ar71xx-generic-dr342-squashfs-sysupgrade.bin",
    "firmwareopenwrtsnapshotinstallurl": null,
    "firmwareopenwrtsnapshotupgradeurl": null,
    "firmwareopenwrtupgradeurl": "https://downloads.openwrt.org/releases/19.07.10/targets/ar71xx/generic/openwrt-19.07.10-ar71xx-generic-dr342-squashfs-sysupgrade.bin",
    "flashmb": "16",
    "forumsearch": "DR342",
    "gitsearch": "DR342",
    "gpios": "-",
    "id": "wallys_dr342",
    "installationmethods": "U-Boot TFTP + serial recovery,see git-commit",
    "jtag": "Yes",
    "ledcount": "7",
    "lede_forum_topic_url": null,
    "model": "DR342",
    "modem": "-",
    "oemdevicehomepageurl": "http://www.wallystech.com/kp/index/pro_detail/id/28.html",
    "owrt_forum_topic_url": null,
    "packagearchitecture": "mips_24kc",
    "page": "toh:hwdata:wallys:wallys_dr342",
    "phoneports": "-",
    "picture": "media:example:genericrouter1.png",
    "pid": "15678134",
    "powersupply": "12-56 VDC, passive PoE 24-56 V",
    "rammb": "64",
    "recoverymethods": "U-Boot TFTP + serial recovery",
    "sataports": "-",
    "serial": "Yes",
    "serialconnectionparameters": "\u00bf",
    "sfp_plus_ports": "\u00bf",
    "sfp_ports": "\u00bf",
    "subtarget": "generic",
    "supportedcurrentrel": "19.07.10",
    "supportedsincecommit": "https://git.lede-project.org/?p=source.git;a=commit;h=c83bdd094ec4722b35811bd64781d8aacddb2344",
    "supportedsincerel": "18.06.0",
    "switch": "-",
    "target": "ar71xx",
    "unsupported_functions": null,
    "usbports": "-",
    "version": null,
    "videoports": "-",
    "vlan": "\u00bf",
    "whereavailable": "\u00bf",
    "wikideviurl": null,
    "wlan24ghz": "-",
    "wlan50ghz": "a/n",
    "wlancomments": null,
    "wlandriver": "ath9k",
    "wlanhardware": "Atheros AR9342"
}